[
  {
    "type": "ENTRYPOINT",
    "named": true,
    "fields": {
      "module": {
        "multiple": false,
        "required": true,
        "types": [
          {
            "type": "module",
            "named": true
          }
        ]
      }
    },
    "children": {
      "multiple": true,
      "required": false,
      "types": [
        {
          "type": "blockcomment",
          "named": true
        },
        {
          "type": "linecomment",
          "named": true
        }
      ]
    }
  },
  {
    "type": "blockcomment",
    "named": true,
    "fields": {},
    "children": {
      "multiple": true,
      "required": false,
      "types": [
        {
          "type": "blockcomment",
          "named": true
        }
      ]
    }
  },
  {
    "type": "blockinstr",
    "named": true,
    "fields": {},
    "children": {
      "multiple": true,
      "required": true,
      "types": [
        {
          "type": "blockcomment",
          "named": true
        },
        {
          "type": "id",
          "named": true
        },
        {
          "type": "instr",
          "named": true
        },
        {
          "type": "linecomment",
          "named": true
        },
        {
          "type": "resulttype",
          "named": true
        }
      ]
    }
  },
  {
    "type": "data",
    "named": true,
    "fields": {},
    "children": {
      "multiple": true,
      "required": false,
      "types": [
        {
          "type": "blockcomment",
          "named": true
        },
        {
          "type": "instr",
          "named": true
        },
        {
          "type": "linecomment",
          "named": true
        },
        {
          "type": "memidx",
          "named": true
        }
      ]
    }
  },
  {
    "type": "datastring",
    "named": false,
    "fields": {}
  },
  {
    "type": "elem",
    "named": true,
    "fields": {},
    "children": {
      "multiple": true,
      "required": false,
      "types": [
        {
          "type": "blockcomment",
          "named": true
        },
        {
          "type": "funcidx",
          "named": true
        },
        {
          "type": "instr",
          "named": true
        },
        {
          "type": "linecomment",
          "named": true
        },
        {
          "type": "tableidx",
          "named": true
        }
      ]
    }
  },
  {
    "type": "elemtype",
    "named": true,
    "fields": {},
    "children": {
      "multiple": true,
      "required": false,
      "types": [
        {
          "type": "blockcomment",
          "named": true
        },
        {
          "type": "linecomment",
          "named": true
        }
      ]
    }
  },
  {
    "type": "export",
    "named": true,
    "fields": {},
    "children": {
      "multiple": true,
      "required": true,
      "types": [
        {
          "type": "blockcomment",
          "named": true
        },
        {
          "type": "exportdesc",
          "named": true
        },
        {
          "type": "linecomment",
          "named": true
        },
        {
          "type": "name",
          "named": true
        }
      ]
    }
  },
  {
    "type": "exportdesc",
    "named": true,
    "fields": {},
    "children": {
      "multiple": true,
      "required": true,
      "types": [
        {
          "type": "blockcomment",
          "named": true
        },
        {
          "type": "funcidx",
          "named": true
        },
        {
          "type": "globalidx",
          "named": true
        },
        {
          "type": "linecomment",
          "named": true
        },
        {
          "type": "memidx",
          "named": true
        },
        {
          "type": "tableidx",
          "named": true
        }
      ]
    }
  },
  {
    "type": "expr",
    "named": false,
    "fields": {},
    "children": {
      "multiple": true,
      "required": true,
      "types": [
        {
          "type": "instr",
          "named": true
        }
      ]
    }
  },
  {
    "type": "func",
    "named": true,
    "fields": {
      "id": {
        "multiple": false,
        "required": false,
        "types": [
          {
            "type": "id",
            "named": true
          }
        ]
      }
    },
    "children": {
      "multiple": true,
      "required": false,
      "types": [
        {
          "type": "blockcomment",
          "named": true
        },
        {
          "type": "inlineExport",
          "named": true
        },
        {
          "type": "inlineImport",
          "named": true
        },
        {
          "type": "instr",
          "named": true
        },
        {
          "type": "linecomment",
          "named": true
        },
        {
          "type": "local",
          "named": true
        }
      ]
    }
  },
  {
    "type": "funcidx",
    "named": true,
    "fields": {},
    "children": {
      "multiple": false,
      "required": true,
      "types": [
        {
          "type": "id",
          "named": true
        },
        {
          "type": "uN",
          "named": true
        }
      ]
    }
  },
  {
    "type": "functype",
    "named": true,
    "fields": {},
    "children": {
      "multiple": true,
      "required": false,
      "types": [
        {
          "type": "blockcomment",
          "named": true
        },
        {
          "type": "linecomment",
          "named": true
        },
        {
          "type": "param",
          "named": true
        },
        {
          "type": "result",
          "named": true
        }
      ]
    }
  },
  {
    "type": "global",
    "named": true,
    "fields": {},
    "children": {
      "multiple": true,
      "required": true,
      "types": [
        {
          "type": "blockcomment",
          "named": true
        },
        {
          "type": "globaltype",
          "named": true
        },
        {
          "type": "id",
          "named": true
        },
        {
          "type": "inlineExport",
          "named": true
        },
        {
          "type": "inlineImport",
          "named": true
        },
        {
          "type": "linecomment",
          "named": true
        }
      ]
    }
  },
  {
    "type": "globalidx",
    "named": true,
    "fields": {},
    "children": {
      "multiple": false,
      "required": true,
      "types": [
        {
          "type": "id",
          "named": true
        },
        {
          "type": "uN",
          "named": true
        }
      ]
    }
  },
  {
    "type": "globaltype",
    "named": true,
    "fields": {},
    "children": {
      "multiple": true,
      "required": true,
      "types": [
        {
          "type": "blockcomment",
          "named": true
        },
        {
          "type": "linecomment",
          "named": true
        },
        {
          "type": "valtype",
          "named": true
        }
      ]
    }
  },
  {
    "type": "id",
    "named": true,
    "fields": {
      "trim": {
        "multiple": false,
        "required": true,
        "types": [
          {
            "type": "idtrimmed",
            "named": true
          }
        ]
      }
    },
    "children": {
      "multiple": true,
      "required": false,
      "types": [
        {
          "type": "blockcomment",
          "named": true
        },
        {
          "type": "linecomment",
          "named": true
        }
      ]
    }
  },
  {
    "type": "import",
    "named": true,
    "fields": {},
    "children": {
      "multiple": true,
      "required": true,
      "types": [
        {
          "type": "blockcomment",
          "named": true
        },
        {
          "type": "globaltype",
          "named": true
        },
        {
          "type": "id",
          "named": true
        },
        {
          "type": "linecomment",
          "named": true
        },
        {
          "type": "memtype",
          "named": true
        },
        {
          "type": "name",
          "named": true
        },
        {
          "type": "tabletype",
          "named": true
        }
      ]
    }
  },
  {
    "type": "inlineExport",
    "named": true,
    "fields": {},
    "children": {
      "multiple": true,
      "required": true,
      "types": [
        {
          "type": "blockcomment",
          "named": true
        },
        {
          "type": "linecomment",
          "named": true
        },
        {
          "type": "name",
          "named": true
        }
      ]
    }
  },
  {
    "type": "inlineImport",
    "named": true,
    "fields": {},
    "children": {
      "multiple": true,
      "required": true,
      "types": [
        {
          "type": "blockcomment",
          "named": true
        },
        {
          "type": "linecomment",
          "named": true
        },
        {
          "type": "name",
          "named": true
        }
      ]
    }
  },
  {
    "type": "instr",
    "named": true,
    "fields": {},
    "children": {
      "multiple": false,
      "required": true,
      "types": [
        {
          "type": "blockinstr",
          "named": true
        },
        {
          "type": "plaininstr",
          "named": true
        }
      ]
    }
  },
  {
    "type": "label",
    "named": false,
    "fields": {
      "trim": {
        "multiple": false,
        "required": true,
        "types": [
          {
            "type": "idtrimmed",
            "named": true
          }
        ]
      }
    },
    "children": {
      "multiple": true,
      "required": false,
      "types": [
        {
          "type": "blockcomment",
          "named": true
        },
        {
          "type": "linecomment",
          "named": true
        }
      ]
    }
  },
  {
    "type": "labelidx",
    "named": true,
    "fields": {},
    "children": {
      "multiple": false,
      "required": true,
      "types": [
        {
          "type": "id",
          "named": true
        },
        {
          "type": "uN",
          "named": true
        }
      ]
    }
  },
  {
    "type": "limits",
    "named": true,
    "fields": {},
    "children": {
      "multiple": true,
      "required": true,
      "types": [
        {
          "type": "blockcomment",
          "named": true
        },
        {
          "type": "linecomment",
          "named": true
        },
        {
          "type": "uN",
          "named": true
        }
      ]
    }
  },
  {
    "type": "linecomment",
    "named": true,
    "fields": {}
  },
  {
    "type": "local",
    "named": true,
    "fields": {},
    "children": {
      "multiple": true,
      "required": false,
      "types": [
        {
          "type": "blockcomment",
          "named": true
        },
        {
          "type": "id",
          "named": true
        },
        {
          "type": "linecomment",
          "named": true
        },
        {
          "type": "valtype",
          "named": true
        }
      ]
    }
  },
  {
    "type": "mem",
    "named": true,
    "fields": {},
    "children": {
      "multiple": true,
      "required": false,
      "types": [
        {
          "type": "blockcomment",
          "named": true
        },
        {
          "type": "id",
          "named": true
        },
        {
          "type": "inlineExport",
          "named": true
        },
        {
          "type": "inlineImport",
          "named": true
        },
        {
          "type": "linecomment",
          "named": true
        },
        {
          "type": "memtype",
          "named": true
        }
      ]
    }
  },
  {
    "type": "memidx",
    "named": true,
    "fields": {},
    "children": {
      "multiple": false,
      "required": true,
      "types": [
        {
          "type": "id",
          "named": true
        },
        {
          "type": "uN",
          "named": true
        }
      ]
    }
  },
  {
    "type": "memtype",
    "named": true,
    "fields": {},
    "children": {
      "multiple": false,
      "required": true,
      "types": [
        {
          "type": "limits",
          "named": true
        }
      ]
    }
  },
  {
    "type": "module",
    "named": true,
    "fields": {
      "id": {
        "multiple": false,
        "required": false,
        "types": [
          {
            "type": "id",
            "named": true
          }
        ]
      },
      "modulefield": {
        "multiple": true,
        "required": false,
        "types": [
          {
            "type": "data",
            "named": true
          },
          {
            "type": "elem",
            "named": true
          },
          {
            "type": "export",
            "named": true
          },
          {
            "type": "func",
            "named": true
          },
          {
            "type": "global",
            "named": true
          },
          {
            "type": "import",
            "named": true
          },
          {
            "type": "mem",
            "named": true
          },
          {
            "type": "start",
            "named": true
          },
          {
            "type": "table",
            "named": true
          },
          {
            "type": "type",
            "named": true
          }
        ]
      }
    },
    "children": {
      "multiple": true,
      "required": false,
      "types": [
        {
          "type": "blockcomment",
          "named": true
        },
        {
          "type": "linecomment",
          "named": true
        }
      ]
    }
  },
  {
    "type": "name",
    "named": true,
    "fields": {},
    "children": {
      "multiple": true,
      "required": false,
      "types": [
        {
          "type": "blockcomment",
          "named": true
        },
        {
          "type": "linecomment",
          "named": true
        }
      ]
    }
  },
  {
    "type": "param",
    "named": true,
    "fields": {},
    "children": {
      "multiple": true,
      "required": false,
      "types": [
        {
          "type": "blockcomment",
          "named": true
        },
        {
          "type": "id",
          "named": true
        },
        {
          "type": "linecomment",
          "named": true
        },
        {
          "type": "valtype",
          "named": true
        }
      ]
    }
  },
  {
    "type": "plaininstr",
    "named": true,
    "fields": {},
    "children": {
      "multiple": true,
      "required": false,
      "types": [
        {
          "type": "blockcomment",
          "named": true
        },
        {
          "type": "funcidx",
          "named": true
        },
        {
          "type": "labelidx",
          "named": true
        },
        {
          "type": "linecomment",
          "named": true
        }
      ]
    }
  },
  {
    "type": "result",
    "named": true,
    "fields": {},
    "children": {
      "multiple": true,
      "required": false,
      "types": [
        {
          "type": "blockcomment",
          "named": true
        },
        {
          "type": "linecomment",
          "named": true
        },
        {
          "type": "valtype",
          "named": true
        }
      ]
    }
  },
  {
    "type": "resulttype",
    "named": true,
    "fields": {},
    "children": {
      "multiple": false,
      "required": true,
      "types": [
        {
          "type": "result",
          "named": true
        }
      ]
    }
  },
  {
    "type": "start",
    "named": true,
    "fields": {},
    "children": {
      "multiple": true,
      "required": true,
      "types": [
        {
          "type": "blockcomment",
          "named": true
        },
        {
          "type": "funcidx",
          "named": true
        },
        {
          "type": "linecomment",
          "named": true
        }
      ]
    }
  },
  {
    "type": "table",
    "named": true,
    "fields": {},
    "children": {
      "multiple": true,
      "required": true,
      "types": [
        {
          "type": "blockcomment",
          "named": true
        },
        {
          "type": "elemtype",
          "named": true
        },
        {
          "type": "funcidx",
          "named": true
        },
        {
          "type": "id",
          "named": true
        },
        {
          "type": "inlineExport",
          "named": true
        },
        {
          "type": "inlineImport",
          "named": true
        },
        {
          "type": "linecomment",
          "named": true
        },
        {
          "type": "tabletype",
          "named": true
        }
      ]
    }
  },
  {
    "type": "tableidx",
    "named": true,
    "fields": {},
    "children": {
      "multiple": false,
      "required": true,
      "types": [
        {
          "type": "id",
          "named": true
        },
        {
          "type": "uN",
          "named": true
        }
      ]
    }
  },
  {
    "type": "tabletype",
    "named": true,
    "fields": {},
    "children": {
      "multiple": true,
      "required": true,
      "types": [
        {
          "type": "elemtype",
          "named": true
        },
        {
          "type": "limits",
          "named": true
        }
      ]
    }
  },
  {
    "type": "type",
    "named": true,
    "fields": {
      "id": {
        "multiple": false,
        "required": false,
        "types": [
          {
            "type": "id",
            "named": true
          }
        ]
      }
    },
    "children": {
      "multiple": true,
      "required": true,
      "types": [
        {
          "type": "blockcomment",
          "named": true
        },
        {
          "type": "functype",
          "named": true
        },
        {
          "type": "linecomment",
          "named": true
        }
      ]
    }
  },
  {
    "type": "typeuse",
    "named": false,
    "fields": {},
    "children": {
      "multiple": true,
      "required": false,
      "types": [
        {
          "type": "blockcomment",
          "named": true
        },
        {
          "type": "id",
          "named": true
        },
        {
          "type": "linecomment",
          "named": true
        },
        {
          "type": "param",
          "named": true
        },
        {
          "type": "result",
          "named": true
        },
        {
          "type": "uN",
          "named": true
        }
      ]
    }
  },
  {
    "type": "uN",
    "named": true,
    "fields": {},
    "children": {
      "multiple": true,
      "required": false,
      "types": [
        {
          "type": "blockcomment",
          "named": true
        },
        {
          "type": "linecomment",
          "named": true
        }
      ]
    }
  },
  {
    "type": "valtype",
    "named": true,
    "fields": {},
    "children": {
      "multiple": true,
      "required": false,
      "types": [
        {
          "type": "blockcomment",
          "named": true
        },
        {
          "type": "linecomment",
          "named": true
        }
      ]
    }
  },
  {
    "type": "\n",
    "named": false
  },
  {
    "type": " ",
    "named": false
  },
  {
    "type": "\"",
    "named": false
  },
  {
    "type": "(",
    "named": false
  },
  {
    "type": "(;",
    "named": false
  },
  {
    "type": ")",
    "named": false
  },
  {
    "type": ".",
    "named": false
  },
  {
    "type": "0x",
    "named": false
  },
  {
    "type": ";)",
    "named": false
  },
  {
    "type": ";;",
    "named": false
  },
  {
    "type": "\\",
    "named": false
  },
  {
    "type": "\\u{",
    "named": false
  },
  {
    "type": "_",
    "named": false
  },
  {
    "type": "block",
    "named": false
  },
  {
    "type": "br",
    "named": false
  },
  {
    "type": "br_if",
    "named": false
  },
  {
    "type": "br_table",
    "named": false
  },
  {
    "type": "call",
    "named": false
  },
  {
    "type": "call_indirect",
    "named": false
  },
  {
    "type": "data",
    "named": false
  },
  {
    "type": "elem",
    "named": false
  },
  {
    "type": "else",
    "named": false
  },
  {
    "type": "end",
    "named": false
  },
  {
    "type": "export",
    "named": false
  },
  {
    "type": "f32",
    "named": false
  },
  {
    "type": "f64",
    "named": false
  },
  {
    "type": "func",
    "named": false
  },
  {
    "type": "funcref",
    "named": false
  },
  {
    "type": "global",
    "named": false
  },
  {
    "type": "i32",
    "named": false
  },
  {
    "type": "i64",
    "named": false
  },
  {
    "type": "idtrimmed",
    "named": true
  },
  {
    "type": "if",
    "named": false
  },
  {
    "type": "import",
    "named": false
  },
  {
    "type": "inf",
    "named": false
  },
  {
    "type": "local",
    "named": false
  },
  {
    "type": "loop",
    "named": false
  },
  {
    "type": "memory",
    "named": false
  },
  {
    "type": "module",
    "named": false
  },
  {
    "type": "mut",
    "named": false
  },
  {
    "type": "nan",
    "named": false
  },
  {
    "type": "nan:0x",
    "named": false
  },
  {
    "type": "nop",
    "named": false
  },
  {
    "type": "offset",
    "named": false
  },
  {
    "type": "param",
    "named": false
  },
  {
    "type": "result",
    "named": false
  },
  {
    "type": "return",
    "named": false
  },
  {
    "type": "start",
    "named": false
  },
  {
    "type": "table",
    "named": false
  },
  {
    "type": "type",
    "named": false
  },
  {
    "type": "unreachable",
    "named": false
  },
  {
    "type": "}",
    "named": false
  }
]